aleksis/apps/hjelp/__init__.py
aleksis/apps/hjelp/admin.py
aleksis/apps/hjelp/apps.py
aleksis/apps/hjelp/forms.py
aleksis/apps/hjelp/frontend/index.js
aleksis/apps/hjelp/frontend/messages/ar.json
aleksis/apps/hjelp/frontend/messages/de.json
aleksis/apps/hjelp/frontend/messages/en.json
aleksis/apps/hjelp/frontend/messages/fr.json
aleksis/apps/hjelp/frontend/messages/la.json
aleksis/apps/hjelp/frontend/messages/nb_NO.json
aleksis/apps/hjelp/frontend/messages/ru.json
aleksis/apps/hjelp/frontend/messages/tr.json
aleksis/apps/hjelp/frontend/messages/uk.json
aleksis/apps/hjelp/locale/ar/LC_MESSAGES/django.mo
aleksis/apps/hjelp/locale/ar/LC_MESSAGES/django.po
aleksis/apps/hjelp/locale/de_DE/LC_MESSAGES/django.mo
aleksis/apps/hjelp/locale/de_DE/LC_MESSAGES/django.po
aleksis/apps/hjelp/locale/fr/LC_MESSAGES/django.mo
aleksis/apps/hjelp/locale/fr/LC_MESSAGES/django.po
aleksis/apps/hjelp/locale/la/LC_MESSAGES/django.mo
aleksis/apps/hjelp/locale/la/LC_MESSAGES/django.po
aleksis/apps/hjelp/locale/nb_NO/LC_MESSAGES/django.mo
aleksis/apps/hjelp/locale/nb_NO/LC_MESSAGES/django.po
aleksis/apps/hjelp/locale/ru/LC_MESSAGES/django.mo
aleksis/apps/hjelp/locale/ru/LC_MESSAGES/django.po
aleksis/apps/hjelp/locale/tr_TR/LC_MESSAGES/django.mo
aleksis/apps/hjelp/locale/tr_TR/LC_MESSAGES/django.po
aleksis/apps/hjelp/locale/uk/LC_MESSAGES/django.mo
aleksis/apps/hjelp/locale/uk/LC_MESSAGES/django.po
aleksis/apps/hjelp/migrations/0001_initial.py
aleksis/apps/hjelp/migrations/0002_change_max_length.py
aleksis/apps/hjelp/migrations/0003_faqsection_position_and_show.py
aleksis/apps/hjelp/migrations/0004_unique_constraints.py
aleksis/apps/hjelp/migrations/0005_update_icon_choices.py
aleksis/apps/hjelp/migrations/0006_add_managed_by_app_label.py
aleksis/apps/hjelp/migrations/0007_drop_sites.py
aleksis/apps/hjelp/migrations/__init__.py
aleksis/apps/hjelp/models.py
aleksis/apps/hjelp/preferences.py
aleksis/apps/hjelp/rules.py
aleksis/apps/hjelp/static/css/hjelp/hjelp.css
aleksis_app_hjelp-4.0.0.dist-info/LICENCE.rst
aleksis_app_hjelp-4.0.0.dist-info/METADATA
aleksis_app_hjelp-4.0.0.dist-info/WHEEL
aleksis_app_hjelp-4.0.0.dist-info/entry_points.txt
aleksis_app_hjelp-4.0.0.dist-info/RECORD
