Metadata-Version: 2.3
Name: AlekSIS-App-Hjelp
Version: 4.0.0
Summary: AlekSIS (School Information System) — App Hjelp (FAQ, issue reporting and support)
License: EUPL-1.2-or-later
Keywords: SIS,education,school,support,feedback
Author: Julian Leucker
Author-email: leuckeju@katharineum.de
Maintainer: Jonathan Weth
Maintainer-email: jonathan.weth@teckids.org
Requires-Python: >=3.10,<4.0
Classifier: Development Status :: 5 - Production/Stable
Classifier: Environment :: Web Environment
Classifier: Framework :: Django :: 3.0
Classifier: Intended Audience :: Education
Classifier: License :: Other/Proprietary License
Classifier: Programming Language :: Python :: 3
Classifier: Programming Language :: Python :: 3.10
Classifier: Programming Language :: Python :: 3.11
Classifier: Programming Language :: Python :: 3.12
Classifier: Programming Language :: Python :: 3.13
Classifier: Topic :: Education
Classifier: Typing :: Typed
Requires-Dist: aleksis-core (>=4.0.0,<5.0.0)
Project-URL: Documentation, https://aleksis.org/AlekSIS/docs/html/
Project-URL: Homepage, https://aleksis.org
Project-URL: Repository, https://edugit.org/AlekSIS/official/AlekSIS-App-Hjelp
